{
  "goal_title": "Intro to Fourier Transform",
  "goal_summary": "Explain frequency decomposition and read the basic transform formula.",
  "nodes": [
    {
      "id": "n1",
      "concept": "Periodic signal",
      "summary": "Recognize when a signal repeats at a fixed interval.",
      "granularity": "topic",
      "est_minutes": 8
    },
    {
      "id": "n2",
      "concept": "Frequency decomposition",
      "summary": "Understand that complex signals can be split into frequency components.",
      "granularity": "topic",
      "est_minutes": 12,
      "is_goal": true
    }
  ],
  "edges": [
    { "from": "n1", "to": "n2", "type": "prereq", "weight": 0.8 }
  ],
  "goal_node_ids": ["n2"]
}
